UniPygame/__init__.py
UniPygame/__main__.py
UniPygame/exceptions.py
UniPygame/lib_main.py
UniPygame/utils.py
unipygame-0.1.dist-info/LICENSE
unipygame-0.1.dist-info/METADATA
unipygame-0.1.dist-info/WHEEL
unipygame-0.1.dist-info/entry_points.txt
unipygame-0.1.dist-info/top_level.txt
unipygame-0.1.dist-info/RECORD
