Metadata-Version: 2.1
Name: unipygame
Version: 0.1
Summary: Pygame Unity style Entity system
Author: The_Herowither
License: MIT License
Project-URL: Homepage, https://github.com/TheHerowither/UniPygame/
Keywords: pygame,unity,addon,enhancement
Classifier: License :: OSI Approved :: MIT License
Classifier: Programming Language :: Python
Classifier: Programming Language :: Python :: 3
Requires-Python: >=3.9
License-File: LICENSE
Requires-Dist: pygame
